ply_convert-0.0.4.data/scripts/ply_convert
ply_convert-0.0.4.data/scripts/ply_convert.py
seplot/__init__.py
seplot/grapher.py
seplot/kw_dictionaries.py
seplot/seplot.py
seplot/seploter.py
seplot/style_dictionaries.py
seplot/styler.py
sio_tools/__init__.py
sio_tools/sio_tools.py
ply_convert-0.0.4.dist-info/LICENCE.md
ply_convert-0.0.4.dist-info/METADATA
ply_convert-0.0.4.dist-info/WHEEL
ply_convert-0.0.4.dist-info/top_level.txt
ply_convert-0.0.4.dist-info/RECORD
