Metadata-Version: 2.1
Name: ply-convert
Version: 0.0.4
Summary: A minimal ply conversion tools
Home-page: https://github.com/SergeDmi/Python-Tools/
Author: Serge Dmitrieff
License: UNKNOWN
Platform: UNKNOWN
Requires-Dist: sklearn
Requires-Dist: numpy
Requires-Dist: plyfile
Requires-Dist: sio-tools
